brightnessctl/__init__.py
brightnessctl/brightnessctl.py
brightnessctl-0.1.0.dist-info/entry_points.txt
brightnessctl-0.1.0.dist-info/LICENSE
brightnessctl-0.1.0.dist-info/WHEEL
brightnessctl-0.1.0.dist-info/METADATA
brightnessctl-0.1.0.dist-info/RECORD
