Metadata-Version: 2.1
Name: brightnessctl
Version: 0.1.0
Summary: Control screen brightness on Linux
Home-page: https://gitlab.com/mattclement/brightnessctl
License: MIT
Author: Matt Clement
Author-email: m@nullroute.host
Requires-Python: >=3.4,<4.0
Classifier: License :: OSI Approved :: MIT License
Classifier: Programming Language :: Python :: 3
Classifier: Programming Language :: Python :: 3.4
Classifier: Programming Language :: Python :: 3.5
Classifier: Programming Language :: Python :: 3.6
Classifier: Programming Language :: Python :: 3.7
Project-URL: Repository, https://gitlab.com/mattclement/brightnessctl
